cxx_image_io-1.1.4.dist-info/WHEEL
cxx_image_io-1.1.4.dist-info/METADATA
cxx_image_io-1.1.4.dist-info/RECORD
cxx_image_io-1.1.4.dist-info/top_level.txt
cxx_image_io-1.1.4.dist-info/licenses/LICENSE.md
cxx_image_io.libs/libexif-61e71f19.so
cxx_image_io.libs/libraw_r-53b13a48.so.24.0.0
cxx_image_io/libexif.so
cxx_image_io/__init__.py
cxx_image_io/libraw_r.so.24.0.0
cxx_image_io/cxx_image.cpython-313-x86_64-linux-gnu.so
cxx_image_io/libraw_r.so
cxx_image_io/cxx_libraw.cpython-313-x86_64-linux-gnu.so
cxx_image_io/libraw_r.so.24
cxx_image_io/io.py
cxx_image_io/utils.py
