Metadata-Version: 2.4
Name: cxx-image-io
Version: 1.1.4
Summary: Image IO APIs for wide range image formats (Camera manufacturer RAW images, jpg, png, tif, dng, bmp, yuv, nv12 ), support Exif, interact nicely with numpy array.
Author-email: Yuan SUN <sunyuan860510@gmail.com>
Maintainer-email: Yuan SUN <sunyuan860510@gmail.com>
License: MIT License
Project-URL: Homepage, https://github.com/sygslhy/image-io
Project-URL: Repository, https://github.com/sygslhy/image-io
Project-URL: Issues, https://github.com/sygslhy/image-io/issues
Project-URL: Releases, https://github.com/sygslhy/image-io/releases
Keywords: imageio,image-io,numpy-image,exif,bmp,camera raw,raw,dng,tif,yuv,nv12,canon,nikon,leica,sony,pentax,kodak
Classifier: Development Status :: 5 - Production/Stable
Classifier: Programming Language :: Python :: 3
Classifier: Programming Language :: Python :: 3 :: Only
Classifier: Programming Language :: Python :: 3.9
Classifier: Programming Language :: Python :: 3.10
Classifier: Programming Language :: Python :: 3.11
Classifier: Programming Language :: Python :: 3.12
Classifier: Programming Language :: Python :: 3.13
Classifier: Programming Language :: C++
Classifier: License :: OSI Approved :: MIT License
Classifier: Operating System :: Microsoft :: Windows
Classifier: Operating System :: POSIX :: Linux
Classifier: Operating System :: MacOS
Classifier: Topic :: Scientific/Engineering
Classifier: Topic :: Software Development
Classifier: Intended Audience :: Science/Research
Classifier: Intended Audience :: Developers
Requires-Python: >=3.9
License-File: LICENSE.md
Requires-Dist: numpy>=2.0.2
Dynamic: license-file
